<?xml version="1.0" encoding="UTF-8" standalone="no" ?>
<Application>

  <Header>
    <Version val="12000"/>
    <WithIsn val="Y"/>
  </Header>

  <ProgramsRepositoryHeaders>
    <Program>
      <Header Description="Main Program" ISN_2="1" LastIsn="1" id="1">
        <Resident val="N"/>
        <SQL val="N"/>
        <ReturnValue>
          <ReturnValueAttr/>
          <ParametersCount val="2"/>
          <ParametersAttributes/>
        </ReturnValue>
        <SqlWhereExist val="N"/>
        <TaskType val="B"/>
        <External val="N"/>
        <Closeopentasks val="N"/>
        <RunProjectAs val="O"/>
        <FormType val="N"/>
        <DotNetObjectExists val="N"/>
        <LastModified _date="734255" _time="49022" date="28/04/2011" time="13:37:02"/>
      </Header>
      <SourceFileTimeStamp _date="734255" _time="38222" date="28/04/2011" time="10:37:02"/>
    </Program>
    <Program>
      <Header Description="----------" ISEMPTY_TSK="1" ISN_2="1" LastIsn="1" id="4">
        <ExecutionRight comp="-1"/>
        <Resident val="N"/>
        <SQL val="N"/>
        <ReturnValue>
          <ReturnValueAttr/>
          <ParametersAttributes/>
        </ReturnValue>
        <SqlWhereExist val="N"/>
        <TaskType val="O"/>
        <External val="N"/>
        <DotNetObjectExists val="N"/>
        <LastModified date="00/00/0000" time="00:00:00"/>
      </Header>
      <SourceFileTimeStamp _date="734085" _time="36338" date="09/11/2010" time="10:05:38"/>
    </Program>
    <Program>
      <Header Description="Browser Check" ISN_2="1" LastIsn="1" id="2">
        <Comment val="Returns the browser name"/>
        <Public val="BrowserCheck"/>
        <ExecutionRight comp="-1"/>
        <Resident val="N"/>
        <SQL val="N"/>
        <ReturnValue>
          <ReturnValueAttr/>
          <ParametersAttributes/>
        </ReturnValue>
        <SqlWhereExist val="N"/>
        <TaskType val="B"/>
        <External val="Y"/>
        <FormType val="N"/>
        <DotNetObjectExists val="N"/>
        <LastModified _date="733734" _time="61687" date="23/11/2009" time="17:08:07"/>
      </Header>
      <SourceFileTimeStamp _date="734084" _time="45345" date="08/11/2010" time="12:35:45"/>
    </Program>
    <Program>
      <Header Description="Get Last Numerator" ISN_2="1" LastIsn="1" id="8">
        <ExecutionRight comp="-1"/>
        <Resident val="N"/>
        <SQL val="N"/>
        <ReturnValue>
          <ReturnValueAttr/>
          <TSK_PARAMS val="2"/>
          <ParametersCount val="2"/>
          <ParametersAttributes>
            <Attr MgAttr="N"/>
            <Attr MgAttr="N"/>
          </ParametersAttributes>
        </ReturnValue>
        <SqlWhereExist val="N"/>
        <TaskType val="B"/>
        <External val="N"/>
        <DotNetObjectExists val="N"/>
        <LastModified _date="732596" _time="46979" date="12/10/2006" time="13:02:59"/>
      </Header>
      <SourceFileTimeStamp _date="734084" _time="45344" date="08/11/2010" time="12:35:44"/>
    </Program>
    <Program>
      <Header Description="Log" ISN_2="1" LastIsn="1" id="51">
        <ExecutionRight comp="-1"/>
        <Resident val="N"/>
        <SQL val="N"/>
        <ReturnValue>
          <ReturnValueAttr/>
          <ParametersAttributes/>
        </ReturnValue>
        <SqlWhereExist val="N"/>
        <TaskType val="B"/>
        <External val="N"/>
        <FormType val="N"/>
        <DotNetObjectExists val="N"/>
        <LastModified _date="734051" _time="41319" date="06/10/2010" time="11:28:39"/>
      </Header>
      <SourceFileTimeStamp _date="734084" _time="45344" date="08/11/2010" time="12:35:44"/>
    </Program>
    <Program>
      <Header Description="LogMessage" ISN_2="1" LastIsn="1" id="103">
        <ExecutionRight comp="-1"/>
        <Resident val="N"/>
        <SQL val="N"/>
        <ReturnValue>
          <ReturnValueAttr/>
          <TSK_PARAMS val="1"/>
          <ParametersCount val="1"/>
          <ParametersAttributes>
            <Attr MgAttr="A"/>
          </ParametersAttributes>
        </ReturnValue>
        <SqlWhereExist val="N"/>
        <TaskType val="B"/>
        <External val="N"/>
        <FormType val="N"/>
        <DotNetObjectExists val="N"/>
        <LastModified _date="734083" _time="58778" date="07/11/2010" time="16:19:38"/>
      </Header>
      <SourceFileTimeStamp _date="734084" _time="45344" date="08/11/2010" time="12:35:44"/>
    </Program>
    <Program>
      <Header Description="readFile" ISN_2="1" LastIsn="1" id="104">
        <ExecutionRight comp="-1"/>
        <Resident val="N"/>
        <SQL val="N"/>
        <ReturnValue>
          <ReturnValueAttr MgAttr="A"/>
          <TSK_PARAMS val="1"/>
          <ParametersCount val="1"/>
          <ParametersAttributes>
            <Attr MgAttr="A"/>
          </ParametersAttributes>
        </ReturnValue>
        <SqlWhereExist val="N"/>
        <TaskType val="B"/>
        <External val="N"/>
        <FormType val="N"/>
        <DotNetObjectExists val="N"/>
        <LastModified _date="734083" _time="61415" date="07/11/2010" time="17:03:35"/>
      </Header>
      <SourceFileTimeStamp _date="734084" _time="45344" date="08/11/2010" time="12:35:44"/>
    </Program>
    <Program>
      <Header Description="Verify logon" ISN_2="1" LastIsn="1" id="81">
        <Public val="VerifyLogon"/>
        <ExecutionRight comp="-1"/>
        <Resident val="N"/>
        <SQL val="N"/>
        <ReturnValue>
          <ReturnValueAttr/>
          <TSK_PARAMS val="1"/>
          <ParametersCount val="1"/>
          <ParametersAttributes>
            <Attr MgAttr="A"/>
          </ParametersAttributes>
        </ReturnValue>
        <SqlWhereExist val="N"/>
        <TaskType val="B"/>
        <External val="Y"/>
        <FormType val="N"/>
        <DotNetObjectExists val="N"/>
        <LastModified _date="733993" _time="58066" date="09/08/2010" time="16:07:46"/>
      </Header>
      <SourceFileTimeStamp _date="734085" _time="35428" date="09/11/2010" time="09:50:28"/>
    </Program>
    <Program>
      <Header Description="----------" ISEMPTY_TSK="1" ISN_2="1" LastIsn="1" id="9">
        <ExecutionRight comp="-1"/>
        <Resident val="N"/>
        <SQL val="N"/>
        <ReturnValue>
          <ReturnValueAttr/>
          <ParametersAttributes/>
        </ReturnValue>
        <SqlWhereExist val="N"/>
        <TaskType val="O"/>
        <External val="N"/>
        <DotNetObjectExists val="N"/>
        <LastModified date="00/00/0000" time="00:00:00"/>
      </Header>
      <SourceFileTimeStamp _date="734085" _time="36326" date="09/11/2010" time="10:05:26"/>
    </Program>
    <Program>
      <Header Description="Logon" ISN_2="1" LastIsn="1" id="71">
        <Public val="Logon"/>
        <ExecutionRight comp="-1"/>
        <Resident val="N"/>
        <SQL val="N"/>
        <ReturnValue>
          <ReturnValueAttr/>
          <TSK_PARAMS val="1"/>
          <ParametersCount val="1"/>
          <ParametersAttributes>
            <Attr MgAttr="A"/>
          </ParametersAttributes>
        </ReturnValue>
        <SqlWhereExist val="N"/>
        <TaskType val="B"/>
        <External val="Y"/>
        <FormType val="N"/>
        <DotNetObjectExists val="N"/>
        <LastModified _date="734083" _time="62258" date="07/11/2010" time="17:17:38"/>
      </Header>
      <SourceFileTimeStamp _date="734084" _time="45344" date="08/11/2010" time="12:35:44"/>
    </Program>
    <Program>
      <Header Description="Menu" ISN_2="1" LastIsn="1" id="41">
        <Public val="Menu"/>
        <ExecutionRight comp="-1"/>
        <Resident val="N"/>
        <SQL val="N"/>
        <ReturnValue>
          <ReturnValueAttr/>
          <ParametersAttributes/>
        </ReturnValue>
        <SqlWhereExist val="N"/>
        <TaskType val="B"/>
        <External val="Y"/>
        <FormType val="N"/>
        <DotNetObjectExists val="N"/>
        <LastModified _date="734083" _time="65456" date="07/11/2010" time="18:10:56"/>
      </Header>
      <SourceFileTimeStamp _date="734084" _time="45343" date="08/11/2010" time="12:35:43"/>
    </Program>
    <Program>
      <Header Description="ProductsList(+selection)" ISN_2="1" LastIsn="1" id="31">
        <Public val="ProductsList"/>
        <ExecutionRight comp="-1"/>
        <Resident val="N"/>
        <SQL val="N"/>
        <ReturnValue>
          <ReturnValueAttr/>
          <TSK_PARAMS val="1"/>
          <ParametersCount val="1"/>
          <ParametersAttributes>
            <Attr MgAttr="N"/>
          </ParametersAttributes>
        </ReturnValue>
        <SqlWhereExist val="N"/>
        <TaskType val="B"/>
        <External val="Y"/>
        <FormType val="N"/>
        <DotNetObjectExists val="N"/>
        <LastModified _date="734085" _time="50224" date="09/11/2010" time="13:57:04"/>
      </Header>
      <SourceFileTimeStamp _date="734085" _time="43024" date="09/11/2010" time="11:57:04"/>
    </Program>
    <Program>
      <Header Description="CustomersList" ISN_2="1" LastIsn="1" id="35">
        <Public val="CustomersList"/>
        <ExecutionRight comp="-1"/>
        <Resident val="N"/>
        <SQL val="N"/>
        <ReturnValue>
          <ReturnValueAttr/>
          <ParametersAttributes/>
        </ReturnValue>
        <SqlWhereExist val="N"/>
        <TaskType val="B"/>
        <External val="Y"/>
        <FormType val="N"/>
        <DotNetObjectExists val="N"/>
        <LastModified _date="734083" _time="66158" date="07/11/2010" time="18:22:38"/>
      </Header>
      <SourceFileTimeStamp _date="734084" _time="45344" date="08/11/2010" time="12:35:44"/>
    </Program>
    <Program>
      <Header Description="OrdersList" ISN_2="1" LastIsn="1" id="37">
        <Public val="OrdersList"/>
        <ExecutionRight comp="-1"/>
        <Resident val="N"/>
        <SQL val="N"/>
        <ReturnValue>
          <ReturnValueAttr/>
          <ParametersAttributes/>
        </ReturnValue>
        <SqlWhereExist val="N"/>
        <TaskType val="B"/>
        <External val="Y"/>
        <FormType val="N"/>
        <DotNetObjectExists val="N"/>
        <LastModified _date="734083" _time="66194" date="07/11/2010" time="18:23:14"/>
      </Header>
      <SourceFileTimeStamp _date="734084" _time="45343" date="08/11/2010" time="12:35:43"/>
    </Program>
    <Program>
      <Header Description="OrderDetails" ISN_2="1" LastIsn="1" id="38">
        <Public val="OrderDetails"/>
        <ExecutionRight comp="-1"/>
        <Resident val="N"/>
        <SQL val="N"/>
        <ReturnValue>
          <ReturnValueAttr/>
          <ParametersAttributes/>
        </ReturnValue>
        <SqlWhereExist val="N"/>
        <TaskType val="B"/>
        <External val="Y"/>
        <FormType val="N"/>
        <DotNetObjectExists val="N"/>
        <LastModified _date="734083" _time="66227" date="07/11/2010" time="18:23:47"/>
      </Header>
      <SourceFileTimeStamp _date="734084" _time="45344" date="08/11/2010" time="12:35:44"/>
    </Program>
    <Program>
      <Header Description="----------" ISEMPTY_TSK="1" ISN_2="1" LastIsn="1" id="32">
        <ExecutionRight comp="-1"/>
        <Resident val="N"/>
        <SQL val="N"/>
        <ReturnValue>
          <ReturnValueAttr/>
          <ParametersAttributes/>
        </ReturnValue>
        <SqlWhereExist val="N"/>
        <TaskType val="O"/>
        <External val="N"/>
        <FormType val="N"/>
        <DotNetObjectExists val="N"/>
        <LastModified date="00/00/0000" time="00:00:00"/>
      </Header>
      <SourceFileTimeStamp _date="734085" _time="36328" date="09/11/2010" time="10:05:28"/>
    </Program>
    <Program>
      <Header Description="Products Data" ISN_2="1" LastIsn="1" id="39">
        <Public val="DataProducts"/>
        <ExecutionRight comp="-1"/>
        <Resident val="N"/>
        <SQL val="N"/>
        <ReturnValue>
          <ReturnValueAttr/>
          <TSK_PARAMS val="4"/>
          <ParametersCount val="4"/>
          <ParametersAttributes>
            <Attr MgAttr="N"/>
            <Attr MgAttr="A"/>
            <Attr MgAttr="N"/>
            <Attr MgAttr="A"/>
          </ParametersAttributes>
        </ReturnValue>
        <SqlWhereExist val="N"/>
        <TaskType val="B"/>
        <External val="Y"/>
        <FormType val="N"/>
        <DotNetObjectExists val="N"/>
        <LastModified _date="734086" _time="40338" date="10/11/2010" time="11:12:18"/>
      </Header>
      <SourceFileTimeStamp _date="734086" _time="33138" date="10/11/2010" time="09:12:18"/>
    </Program>
    <Program>
      <Header Description="Customers Data" ISN_2="1" LastIsn="1" id="53">
        <Public val="DataCustomers"/>
        <ExecutionRight comp="-1"/>
        <Resident val="N"/>
        <SQL val="N"/>
        <ReturnValue>
          <ReturnValueAttr/>
          <TSK_PARAMS val="4"/>
          <ParametersCount val="4"/>
          <ParametersAttributes>
            <Attr MgAttr="N"/>
            <Attr MgAttr="A"/>
            <Attr MgAttr="N"/>
            <Attr MgAttr="A"/>
          </ParametersAttributes>
        </ReturnValue>
        <SqlWhereExist val="N"/>
        <TaskType val="B"/>
        <External val="Y"/>
        <FormType val="N"/>
        <DotNetObjectExists val="N"/>
        <LastModified _date="734086" _time="40324" date="10/11/2010" time="11:12:04"/>
      </Header>
      <SourceFileTimeStamp _date="734086" _time="33124" date="10/11/2010" time="09:12:04"/>
    </Program>
    <Program>
      <Header Description="Orders Data" ISN_2="1" LastIsn="4" id="54">
        <Public val="DataOrders"/>
        <ExecutionRight comp="-1"/>
        <Resident val="N"/>
        <SQL val="N"/>
        <ReturnValue>
          <ReturnValueAttr/>
          <TSK_PARAMS val="5"/>
          <ParametersCount val="5"/>
          <ParametersAttributes>
            <Attr MgAttr="N"/>
            <Attr MgAttr="A"/>
            <Attr MgAttr="N"/>
            <Attr MgAttr="A"/>
            <Attr MgAttr="A"/>
          </ParametersAttributes>
        </ReturnValue>
        <SqlWhereExist val="N"/>
        <TaskType val="B"/>
        <External val="Y"/>
        <FormType val="N"/>
        <DotNetObjectExists val="N"/>
        <LastModified _date="734255" _time="49026" date="28/04/2011" time="13:37:06"/>
      </Header>
      <SourceFileTimeStamp _date="734086" _time="33161" date="10/11/2010" time="09:12:41"/>
    </Program>
    <Program>
      <Header Description="----------" ISEMPTY_TSK="1" ISN_2="1" LastIsn="1" id="60">
        <ExecutionRight comp="-1"/>
        <Resident val="N"/>
        <SQL val="N"/>
        <ReturnValue>
          <ReturnValueAttr/>
          <ParametersAttributes/>
        </ReturnValue>
        <SqlWhereExist val="N"/>
        <TaskType val="O"/>
        <External val="N"/>
        <FormType val="N"/>
        <DotNetObjectExists val="N"/>
        <LastModified date="00/00/0000" time="00:00:00"/>
      </Header>
      <SourceFileTimeStamp _date="734085" _time="36331" date="09/11/2010" time="10:05:31"/>
    </Program>
    <Program>
      <Header Description="Order Update" ISN_2="1" LastIsn="7" id="50">
        <Public val="OrderUpdate"/>
        <ExecutionRight comp="-1"/>
        <Resident val="N"/>
        <SQL val="N"/>
        <ReturnValue>
          <ReturnValueAttr/>
          <TSK_PARAMS val="5"/>
          <ParametersCount val="5"/>
          <ParametersAttributes>
            <Attr MgAttr="N"/>
            <Attr MgAttr="D"/>
            <Attr MgAttr="N"/>
            <Attr MgAttr="A"/>
            <Attr MgAttr="O"/>
          </ParametersAttributes>
        </ReturnValue>
        <SqlWhereExist val="N"/>
        <TaskType val="B"/>
        <External val="Y"/>
        <FormType val="N"/>
        <DotNetObjectExists val="N"/>
        <LastModified _date="734255" _time="49026" date="28/04/2011" time="13:37:06"/>
      </Header>
      <SourceFileTimeStamp _date="734086" _time="31608" date="10/11/2010" time="08:46:48"/>
    </Program>
    <Program>
      <Header Description="----------" ISEMPTY_TSK="1" ISN_2="1" LastIsn="1" id="76">
        <ExecutionRight comp="-1"/>
        <Resident val="N"/>
        <SQL val="N"/>
        <ReturnValue>
          <ReturnValueAttr/>
          <ParametersAttributes/>
        </ReturnValue>
        <SqlWhereExist val="N"/>
        <TaskType val="O"/>
        <External val="N"/>
        <FormType val="N"/>
        <DotNetObjectExists val="N"/>
        <LastModified date="00/00/0000" time="00:00:00"/>
      </Header>
      <SourceFileTimeStamp _date="734085" _time="36335" date="09/11/2010" time="10:05:35"/>
    </Program>
  </ProgramsRepositoryHeaders>

</Application>
